[{"pv_ocorrencia_id": 447170, "start_timestamp": 1600088400.0, "finish_timestamp": 1600095600.0, "rooms": []}, {"pv_ocorrencia_id": 443045, "start_timestamp": 1600090200.0, "finish_timestamp": 1600097400.0, "rooms": []}, {"pv_ocorrencia_id": 445311, "start_timestamp": 1600124400.0, "finish_timestamp": 1600131600.0, "rooms": []}, {"pv_ocorrencia_id": 444285, "start_timestamp": 1600210800.0, "finish_timestamp": 1600218000.0, "rooms": []}, {"pv_ocorrencia_id": 443034, "start_timestamp": 1600263000.0, "finish_timestamp": 1600270200.0, "rooms": []}, {"pv_ocorrencia_id": 443035, "start_timestamp": 1600349400.0, "finish_timestamp": 1600356600.0, "rooms": []}, {"pv_ocorrencia_id": 444285, "start_timestamp": 1600383600.0, "finish_timestamp": 1600390800.0, "rooms": []}, {"pv_ocorrencia_id": 443047, "start_timestamp": 1600435800.0, "finish_timestamp": 1600443000.0, "rooms": []}, {"pv_ocorrencia_id": 443044, "start_timestamp": 1600435800.0, "finish_timestamp": 1600443000.0, "rooms": []}, {"pv_ocorrencia_id": 443022, "start_timestamp": 1598950800.0, "finish_timestamp": 1598958000.0, "rooms": []}, {"pv_ocorrencia_id": 447170, "start_timestamp": 1598965200.0, "finish_timestamp": 1598972400.0, "rooms": []}, {"pv_ocorrencia_id": 443034, "start_timestamp": 1598967000.0, "finish_timestamp": 1598974200.0, "rooms": []}, {"pv_ocorrencia_id": 443041, "start_timestamp": 1599037200.0, "finish_timestamp": 1599044400.0, "rooms": []}, {"pv_ocorrencia_id": 443045, "start_timestamp": 1599053400.0, "finish_timestamp": 1599060600.0, "rooms": []}, {"pv_ocorrencia_id": 445311, "start_timestamp": 1599087600.0, "finish_timestamp": 1599094800.0, "rooms": []}, {"pv_ocorrencia_id": 443021, "start_timestamp": 1599123600.0, "finish_timestamp": 1599130800.0, "rooms": []}, {"pv_ocorrencia_id": 443040, "start_timestamp": 1599210000.0, "finish_timestamp": 1599217200.0, "rooms": []}, {"pv_ocorrencia_id": 443035, "start_timestamp": 1599226200.0, "finish_timestamp": 1599233400.0, "rooms": []}, {"pv_ocorrencia_id": 443044, "start_timestamp": 1599485400.0, "finish_timestamp": 1599492600.0, "rooms": []}, {"pv_ocorrencia_id": 444285, "start_timestamp": 1599519600.0, "finish_timestamp": 1599526800.0, "rooms": []}, {"pv_ocorrencia_id": 443027, "start_timestamp": 1599555600.0, "finish_timestamp": 1599562800.0, "rooms": []}, {"pv_ocorrencia_id": 443033, "start_timestamp": 1599555600.0, "finish_timestamp": 1599562800.0, "rooms": []}, {"pv_ocorrencia_id": 444286, "start_timestamp": 1599606000.0, "finish_timestamp": 1599613200.0, "rooms": []}, {"pv_ocorrencia_id": 446861, "start_timestamp": 1599642000.0, "finish_timestamp": 1599649200.0, "rooms": []}, {"pv_ocorrencia_id": 444284, "start_timestamp": 1599692400.0, "finish_timestamp": 1599699600.0, "rooms": []}, {"pv_ocorrencia_id": 443026, "start_timestamp": 1599728400.0, "finish_timestamp": 1599735600.0, "rooms": []}, {"pv_ocorrencia_id": 443047, "start_timestamp": 1599744600.0, "finish_timestamp": 1599751800.0, "rooms": []}, {"pv_ocorrencia_id": 445202, "start_timestamp": 1599778800.0, "finish_timestamp": 1599786000.0, "rooms": []}, {"pv_ocorrencia_id": 442986, "start_timestamp": 1599831000.0, "finish_timestamp": 1599838200.0, "rooms": []}, {"pv_ocorrencia_id": 436797, "start_timestamp": 1599474600.0, "finish_timestamp": 1599480000.0, "rooms": ["B221"]}, {"pv_ocorrencia_id": 436558, "start_timestamp": 1599474600.0, "finish_timestamp": 1599480000.0, "rooms": []}, {"pv_ocorrencia_id": 436845, "start_timestamp": 1600079400.0, "finish_timestamp": 1600084800.0, "rooms": []}, {"pv_ocorrencia_id": 436901, "start_timestamp": 1600252200.0, "finish_timestamp": 1600257600.0, "rooms": []}, {"pv_ocorrencia_id": 436901, "start_timestamp": 1600770600.0, "finish_timestamp": 1600776000.0, "rooms": []}, {"pv_ocorrencia_id": 436882, "start_timestamp": 1600869600.0, "finish_timestamp": 1600875000.0, "rooms": []}, {"pv_ocorrencia_id": 436883, "start_timestamp": 1601647200.0, "finish_timestamp": 1601652600.0, "rooms": []}, {"pv_ocorrencia_id": 436901, "start_timestamp": 1600252200.0, "finish_timestamp": 1600257600.0, "rooms": []}, {"pv_ocorrencia_id": 436901, "start_timestamp": 1600770600.0, "finish_timestamp": 1600776000.0, "rooms": []}]