[{"pv_ocorrencia_id": 443047, "start_timestamp": 1591138800.0, "finish_timestamp": 1591146000.0, "rooms": []}, {"pv_ocorrencia_id": 442986, "start_timestamp": 1591225200.0, "finish_timestamp": 1591232400.0, "rooms": []}, {"pv_ocorrencia_id": 447170, "start_timestamp": 1591225200.0, "finish_timestamp": 1591232400.0, "rooms": []}, {"pv_ocorrencia_id": 443033, "start_timestamp": 1591398000.0, "finish_timestamp": 1591405200.0, "rooms": []}, {"pv_ocorrencia_id": 443045, "start_timestamp": 1591570800.0, "finish_timestamp": 1591578000.0, "rooms": []}, {"pv_ocorrencia_id": 445311, "start_timestamp": 1591570800.0, "finish_timestamp": 1591578000.0, "rooms": []}, {"pv_ocorrencia_id": 443035, "start_timestamp": 1591916400.0, "finish_timestamp": 1591923600.0, "rooms": []}, {"pv_ocorrencia_id": 443022, "start_timestamp": 1591916400.0, "finish_timestamp": 1591923600.0, "rooms": []}, {"pv_ocorrencia_id": 444285, "start_timestamp": 1592175600.0, "finish_timestamp": 1592182800.0, "rooms": []}, {"pv_ocorrencia_id": 443044, "start_timestamp": 1592262000.0, "finish_timestamp": 1592269200.0, "rooms": []}, {"pv_ocorrencia_id": 443034, "start_timestamp": 1592434800.0, "finish_timestamp": 1592442000.0, "rooms": []}, {"pv_ocorrencia_id": 443047, "start_timestamp": 1593039600.0, "finish_timestamp": 1593046800.0, "rooms": []}, {"pv_ocorrencia_id": 447170, "start_timestamp": 1593126000.0, "finish_timestamp": 1593133200.0, "rooms": []}, {"pv_ocorrencia_id": 442986, "start_timestamp": 1593126000.0, "finish_timestamp": 1593133200.0, "rooms": []}, {"pv_ocorrencia_id": 443033, "start_timestamp": 1593212400.0, "finish_timestamp": 1593219600.0, "rooms": []}, {"pv_ocorrencia_id": 443045, "start_timestamp": 1593385200.0, "finish_timestamp": 1593392400.0, "rooms": []}, {"pv_ocorrencia_id": 445311, "start_timestamp": 1593471600.0, "finish_timestamp": 1593478800.0, "rooms": []}, {"pv_ocorrencia_id": 443035, "start_timestamp": 1593644400.0, "finish_timestamp": 1593651600.0, "rooms": []}, {"pv_ocorrencia_id": 443022, "start_timestamp": 1593730800.0, "finish_timestamp": 1593738000.0, "rooms": []}, {"pv_ocorrencia_id": 443044, "start_timestamp": 1593990000.0, "finish_timestamp": 1593997200.0, "rooms": []}, {"pv_ocorrencia_id": 444285, "start_timestamp": 1594076400.0, "finish_timestamp": 1594083600.0, "rooms": []}, {"pv_ocorrencia_id": 442983, "start_timestamp": 1594076400.0, "finish_timestamp": 1594083600.0, "rooms": []}, {"pv_ocorrencia_id": 443023, "start_timestamp": 1594162800.0, "finish_timestamp": 1594170000.0, "rooms": []}, {"pv_ocorrencia_id": 443034, "start_timestamp": 1594162800.0, "finish_timestamp": 1594170000.0, "rooms": []}, {"pv_ocorrencia_id": 442987, "start_timestamp": 1594249200.0, "finish_timestamp": 1594256400.0, "rooms": []}]