[{"pv_ocorrencia_id": 460221, "start_timestamp": 1611649800.0, "finish_timestamp": 1611655200.0, "rooms": ["B304"]}, {"pv_ocorrencia_id": 460223, "start_timestamp": 1611909000.0, "finish_timestamp": 1611914400.0, "rooms": ["B304"]}, {"pv_ocorrencia_id": 460234, "start_timestamp": 1611919800.0, "finish_timestamp": 1611925200.0, "rooms": ["B216"]}, {"pv_ocorrencia_id": 460222, "start_timestamp": 1612179000.0, "finish_timestamp": 1612184400.0, "rooms": ["B214"]}, {"pv_ocorrencia_id": 460224, "start_timestamp": 1612513800.0, "finish_timestamp": 1612519200.0, "rooms": ["B120"]}, {"pv_ocorrencia_id": 460235, "start_timestamp": 1612513800.0, "finish_timestamp": 1612519200.0, "rooms": ["B113"]}]