[{"pv_ocorrencia_id": 436813, "start_timestamp": 1581066000.0, "finish_timestamp": 1581076800.0, "rooms": ["B335"]}, {"pv_ocorrencia_id": 436763, "start_timestamp": 1581066000.0, "finish_timestamp": 1581076800.0, "rooms": ["B332"]}, {"pv_ocorrencia_id": 436786, "start_timestamp": 1581082200.0, "finish_timestamp": 1581087600.0, "rooms": ["B335"]}, {"pv_ocorrencia_id": 436547, "start_timestamp": 1581082200.0, "finish_timestamp": 1581093000.0, "rooms": ["B225"]}, {"pv_ocorrencia_id": 436809, "start_timestamp": 1581094800.0, "finish_timestamp": 1581105600.0, "rooms": ["B330"]}]