[{"pv_ocorrencia_id": 488646, "start_timestamp": 1655074800.0, "finish_timestamp": 1655082000.0, "rooms": []}, {"pv_ocorrencia_id": 488582, "start_timestamp": 1655074800.0, "finish_timestamp": 1655082000.0, "rooms": []}, {"pv_ocorrencia_id": 488629, "start_timestamp": 1655161200.0, "finish_timestamp": 1655168400.0, "rooms": []}, {"pv_ocorrencia_id": 488638, "start_timestamp": 1655161200.0, "finish_timestamp": 1655168400.0, "rooms": []}, {"pv_ocorrencia_id": 488643, "start_timestamp": 1655247600.0, "finish_timestamp": 1655254800.0, "rooms": []}, {"pv_ocorrencia_id": 488702, "start_timestamp": 1655420400.0, "finish_timestamp": 1655427600.0, "rooms": []}, {"pv_ocorrencia_id": 488631, "start_timestamp": 1655506800.0, "finish_timestamp": 1655514000.0, "rooms": []}, {"pv_ocorrencia_id": 488645, "start_timestamp": 1655679600.0, "finish_timestamp": 1655686800.0, "rooms": []}, {"pv_ocorrencia_id": 488642, "start_timestamp": 1655679600.0, "finish_timestamp": 1655686800.0, "rooms": []}, {"pv_ocorrencia_id": 488627, "start_timestamp": 1655766000.0, "finish_timestamp": 1655773200.0, "rooms": []}, {"pv_ocorrencia_id": 488641, "start_timestamp": 1655938800.0, "finish_timestamp": 1655946000.0, "rooms": []}, {"pv_ocorrencia_id": 488639, "start_timestamp": 1656284400.0, "finish_timestamp": 1656291600.0, "rooms": []}, {"pv_ocorrencia_id": 488630, "start_timestamp": 1656370800.0, "finish_timestamp": 1656378000.0, "rooms": []}, {"pv_ocorrencia_id": 488628, "start_timestamp": 1656630000.0, "finish_timestamp": 1656637200.0, "rooms": []}, {"pv_ocorrencia_id": 488643, "start_timestamp": 1656716400.0, "finish_timestamp": 1656723600.0, "rooms": []}, {"pv_ocorrencia_id": 488646, "start_timestamp": 1656889200.0, "finish_timestamp": 1656896400.0, "rooms": []}, {"pv_ocorrencia_id": 488629, "start_timestamp": 1656889200.0, "finish_timestamp": 1656896400.0, "rooms": []}, {"pv_ocorrencia_id": 488582, "start_timestamp": 1656889200.0, "finish_timestamp": 1656896400.0, "rooms": []}, {"pv_ocorrencia_id": 488638, "start_timestamp": 1656975600.0, "finish_timestamp": 1656982800.0, "rooms": []}, {"pv_ocorrencia_id": 488631, "start_timestamp": 1657062000.0, "finish_timestamp": 1657069200.0, "rooms": []}, {"pv_ocorrencia_id": 488642, "start_timestamp": 1657234800.0, "finish_timestamp": 1657242000.0, "rooms": []}, {"pv_ocorrencia_id": 488627, "start_timestamp": 1657234800.0, "finish_timestamp": 1657242000.0, "rooms": []}, {"pv_ocorrencia_id": 488641, "start_timestamp": 1657494000.0, "finish_timestamp": 1657501200.0, "rooms": []}, {"pv_ocorrencia_id": 488630, "start_timestamp": 1657580400.0, "finish_timestamp": 1657587600.0, "rooms": []}, {"pv_ocorrencia_id": 488639, "start_timestamp": 1657666800.0, "finish_timestamp": 1657674000.0, "rooms": []}, {"pv_ocorrencia_id": 488628, "start_timestamp": 1657753200.0, "finish_timestamp": 1657760400.0, "rooms": []}, {"pv_ocorrencia_id": 488645, "start_timestamp": 1657839600.0, "finish_timestamp": 1657846800.0, "rooms": []}, {"pv_ocorrencia_id": 488702, "start_timestamp": 1657926000.0, "finish_timestamp": 1657933200.0, "rooms": []}]