[{"acronym": "IADP", "curricular_year": 1, "name": "Introduction to data analysis in Python", "pv_ocorrencia_id": 489602, "semester": "2", "url": "https://sigarra.up.pt/feup/en/ucurr_geral.ficha_uc_view?pv_ocorrencia_id=489602"}, {"acronym": "AMII", "curricular_year": 1, "name": "Calculus II", "pv_ocorrencia_id": 484365, "semester": "2", "url": "https://sigarra.up.pt/feup/en/ucurr_geral.ficha_uc_view?pv_ocorrencia_id=484365"}, {"acronym": "FI", "curricular_year": 1, "name": "Physics I", "pv_ocorrencia_id": 484366, "semester": "2", "url": "https://sigarra.up.pt/feup/en/ucurr_geral.ficha_uc_view?pv_ocorrencia_id=484366"}, {"acronym": "PMN", "curricular_year": 1, "name": "Numerical Methods and Programming", "pv_ocorrencia_id": 484367, "semester": "2", "url": "https://sigarra.up.pt/feup/en/ucurr_geral.ficha_uc_view?pv_ocorrencia_id=484367"}, {"acronym": "QII", "curricular_year": 1, "name": "Chemistry II", "pv_ocorrencia_id": 484368, "semester": "2", "url": "https://sigarra.up.pt/feup/en/ucurr_geral.ficha_uc_view?pv_ocorrencia_id=484368"}, {"acronym": "QOII", "curricular_year": 1, "name": "Organic Chemistry II", "pv_ocorrencia_id": 484369, "semester": "2", "url": "https://sigarra.up.pt/feup/en/ucurr_geral.ficha_uc_view?pv_ocorrencia_id=484369"}, {"acronym": "SCT", "curricular_year": 1, "name": "Seminars in Transferable Skills", "pv_ocorrencia_id": 484370, "semester": "2", "url": "https://sigarra.up.pt/feup/en/ucurr_geral.ficha_uc_view?pv_ocorrencia_id=484370"}, {"acronym": "CEM", "curricular_year": 2, "name": "Materials Science and Engineering", "pv_ocorrencia_id": 484371, "semester": "2", "url": "https://sigarra.up.pt/feup/en/ucurr_geral.ficha_uc_view?pv_ocorrencia_id=484371"}, {"acronym": "CB", "curricular_year": 2, "name": "Biological Sciences", "pv_ocorrencia_id": 484372, "semester": "2", "url": "https://sigarra.up.pt/feup/en/ucurr_geral.ficha_uc_view?pv_ocorrencia_id=484372"}, {"acronym": "MEAEQ", "curricular_year": 2, "name": "Statistical Methods Applied to Chemical Engineering", "pv_ocorrencia_id": 484373, "semester": "2", "url": "https://sigarra.up.pt/feup/en/ucurr_geral.ficha_uc_view?pv_ocorrencia_id=484373"}, {"acronym": "TERII", "curricular_year": 2, "name": "Thermodynamics II", "pv_ocorrencia_id": 484374, "semester": "2", "url": "https://sigarra.up.pt/feup/en/ucurr_geral.ficha_uc_view?pv_ocorrencia_id=484374"}, {"acronym": "TC", "curricular_year": 2, "name": "Heat Transfer", "pv_ocorrencia_id": 484375, "semester": "2", "url": "https://sigarra.up.pt/feup/en/ucurr_geral.ficha_uc_view?pv_ocorrencia_id=484375"}, {"acronym": "CEP", "curricular_year": 3, "name": "Polymer Science and Engineering", "pv_ocorrencia_id": 490129, "semester": "2", "url": "https://sigarra.up.pt/feup/en/ucurr_geral.ficha_uc_view?pv_ocorrencia_id=490129"}, {"acronym": "AIEQ", "curricular_year": 3, "name": "Software Tools for Chemical Engineering", "pv_ocorrencia_id": 490130, "semester": "2", "url": "https://sigarra.up.pt/feup/en/ucurr_geral.ficha_uc_view?pv_ocorrencia_id=490130"}, {"acronym": "MPSAC", "curricular_year": 2, "name": "Mini projects on machine learning and control systems", "pv_ocorrencia_id": 489746, "semester": "2", "url": "https://sigarra.up.pt/feup/en/ucurr_geral.ficha_uc_view?pv_ocorrencia_id=489746"}, {"acronym": "ERII", "curricular_year": 3, "name": "Reaction Engineering II", "pv_ocorrencia_id": 484395, "semester": "2", "url": "https://sigarra.up.pt/feup/en/ucurr_geral.ficha_uc_view?pv_ocorrencia_id=484395"}, {"acronym": "LFT", "curricular_year": 3, "name": "Transport Phenomena Laboratories", "pv_ocorrencia_id": 484396, "semester": "2", "url": "https://sigarra.up.pt/feup/en/ucurr_geral.ficha_uc_view?pv_ocorrencia_id=484396"}, {"acronym": "PSII", "curricular_year": 3, "name": "Separation Processes II", "pv_ocorrencia_id": 484397, "semester": "2", "url": "https://sigarra.up.pt/feup/en/ucurr_geral.ficha_uc_view?pv_ocorrencia_id=484397"}, {"acronym": "QFS", "curricular_year": 3, "name": "Physical Chemistry of Surfaces", "pv_ocorrencia_id": 484398, "semester": "2", "url": "https://sigarra.up.pt/feup/en/ucurr_geral.ficha_uc_view?pv_ocorrencia_id=484398"}, {"acronym": "EAV", "curricular_year": 1, "name": "Lifelong Employability", "pv_ocorrencia_id": 489282, "semester": "2", "url": "http://sigarra.up.pt/fpceup/en/ucurr_geral.ficha_uc_view?pv_ocorrencia_id=489282"}, {"acronym": "IPMATLAB", "curricular_year": 1, "name": "Introdu\u00e7\u00e3o \u00e0 programa\u00e7\u00e3o em MATLAB", "pv_ocorrencia_id": 489666, "semester": "2", "url": "https://sigarra.up.pt/feup/en/ucurr_geral.ficha_uc_view?pv_ocorrencia_id=489666"}, {"acronym": "IO", "curricular_year": 1, "name": "Introduction to optimization", "pv_ocorrencia_id": 489668, "semester": "2", "url": "https://sigarra.up.pt/feup/en/ucurr_geral.ficha_uc_view?pv_ocorrencia_id=489668"}, {"acronym": "IADE", "curricular_year": 1, "name": "Introduction to data analysis in Excel", "pv_ocorrencia_id": 489303, "semester": "2", "url": "https://sigarra.up.pt/feup/en/ucurr_geral.ficha_uc_view?pv_ocorrencia_id=489303"}, {"acronym": "CP", "curricular_year": 1, "name": "Transferable Skills: Professional Communication", "pv_ocorrencia_id": 489823, "semester": "2", "url": "https://sigarra.up.pt/feup/en/ucurr_geral.ficha_uc_view?pv_ocorrencia_id=489823"}, {"acronym": "IR", "curricular_year": 1, "name": "Introduction to Robotics", "pv_ocorrencia_id": 489705, "semester": "2", "url": "https://sigarra.up.pt/feup/en/ucurr_geral.ficha_uc_view?pv_ocorrencia_id=489705"}]