[{"acronym": "AMAT2", "curricular_year": 1, "name": "Mathematical Analysis II", "pv_ocorrencia_id": 455231, "semester": "2", "url": "https://sigarra.up.pt/feup/en/ucurr_geral.ficha_uc_view?pv_ocorrencia_id=455231"}, {"acronym": "ANUM", "curricular_year": 1, "name": "Numerical Analysis", "pv_ocorrencia_id": 455232, "semester": "2", "url": "https://sigarra.up.pt/feup/en/ucurr_geral.ficha_uc_view?pv_ocorrencia_id=455232"}, {"acronym": "TOPO", "curricular_year": 1, "name": "Topography", "pv_ocorrencia_id": 455233, "semester": "2", "url": "https://sigarra.up.pt/feup/en/ucurr_geral.ficha_uc_view?pv_ocorrencia_id=455233"}, {"acronym": "MECA1", "curricular_year": 1, "name": "Mechanics 1", "pv_ocorrencia_id": 455234, "semester": "2", "url": "https://sigarra.up.pt/feup/en/ucurr_geral.ficha_uc_view?pv_ocorrencia_id=455234"}, {"acronym": "EGES", "curricular_year": 1, "name": "Economics and Management", "pv_ocorrencia_id": 455235, "semester": "2", "url": "https://sigarra.up.pt/feup/en/ucurr_geral.ficha_uc_view?pv_ocorrencia_id=455235"}, {"acronym": "ARQU", "curricular_year": 2, "name": "Architecture", "pv_ocorrencia_id": 455261, "semester": "2", "url": "https://sigarra.up.pt/feup/en/ucurr_geral.ficha_uc_view?pv_ocorrencia_id=455261"}, {"acronym": "FISI", "curricular_year": 2, "name": "Physics", "pv_ocorrencia_id": 455262, "semester": "2", "url": "https://sigarra.up.pt/feup/en/ucurr_geral.ficha_uc_view?pv_ocorrencia_id=455262"}, {"acronym": "HGER1", "curricular_year": 2, "name": "General Hydraulics I", "pv_ocorrencia_id": 455263, "semester": "2", "url": "https://sigarra.up.pt/feup/en/ucurr_geral.ficha_uc_view?pv_ocorrencia_id=455263"}, {"acronym": "RMAT2", "curricular_year": 2, "name": "Strength of Materials II", "pv_ocorrencia_id": 455264, "semester": "2", "url": "https://sigarra.up.pt/feup/en/ucurr_geral.ficha_uc_view?pv_ocorrencia_id=455264"}, {"acronym": "ESTA", "curricular_year": 2, "name": "Statistics", "pv_ocorrencia_id": 455265, "semester": "2", "url": "https://sigarra.up.pt/feup/en/ucurr_geral.ficha_uc_view?pv_ocorrencia_id=455265"}, {"acronym": "MCON2", "curricular_year": 3, "name": "Construction Materials II", "pv_ocorrencia_id": 455271, "semester": "2", "url": "https://sigarra.up.pt/feup/en/ucurr_geral.ficha_uc_view?pv_ocorrencia_id=455271"}, {"acronym": "TEST2", "curricular_year": 3, "name": "Structural Analysis II", "pv_ocorrencia_id": 455272, "semester": "2", "url": "https://sigarra.up.pt/feup/en/ucurr_geral.ficha_uc_view?pv_ocorrencia_id=455272"}, {"acronym": "HRHI", "curricular_year": 3, "name": "Hydrology and Water Resources", "pv_ocorrencia_id": 455273, "semester": "2", "url": "https://sigarra.up.pt/feup/en/ucurr_geral.ficha_uc_view?pv_ocorrencia_id=455273"}, {"acronym": "TCON", "curricular_year": 3, "name": "Technology of Construction", "pv_ocorrencia_id": 455274, "semester": "2", "url": "https://sigarra.up.pt/feup/en/ucurr_geral.ficha_uc_view?pv_ocorrencia_id=455274"}, {"acronym": "PTER", "curricular_year": 3, "name": "Territorial Planning", "pv_ocorrencia_id": 455275, "semester": "2", "url": "https://sigarra.up.pt/feup/en/ucurr_geral.ficha_uc_view?pv_ocorrencia_id=455275"}, {"acronym": "EBET2", "curricular_year": 4, "name": "Structural Concrete II", "pv_ocorrencia_id": 455281, "semester": "2", "url": "https://sigarra.up.pt/feup/en/ucurr_geral.ficha_uc_view?pv_ocorrencia_id=455281"}, {"acronym": "MSOL2", "curricular_year": 4, "name": "Soil Mechanics II", "pv_ocorrencia_id": 455282, "semester": "2", "url": "https://sigarra.up.pt/feup/en/ucurr_geral.ficha_uc_view?pv_ocorrencia_id=455282"}, {"acronym": "AUTR", "curricular_year": 4, "name": "Urban Environment and Transport Planning", "pv_ocorrencia_id": 455283, "semester": "2", "url": "https://sigarra.up.pt/feup/en/ucurr_geral.ficha_uc_view?pv_ocorrencia_id=455283"}, {"acronym": "VCOM2", "curricular_year": 4, "name": "Roads II", "pv_ocorrencia_id": 455284, "semester": "2", "url": "https://sigarra.up.pt/feup/en/ucurr_geral.ficha_uc_view?pv_ocorrencia_id=455284"}, {"acronym": "GOSE", "curricular_year": 4, "name": "Construction Management and Safety", "pv_ocorrencia_id": 455285, "semester": "2", "url": "https://sigarra.up.pt/feup/en/ucurr_geral.ficha_uc_view?pv_ocorrencia_id=455285"}, {"acronym": "DEST", "curricular_year": 5, "name": "Thesis in Structures", "pv_ocorrencia_id": 455343, "semester": "2", "url": "https://sigarra.up.pt/feup/en/ucurr_geral.ficha_uc_view?pv_ocorrencia_id=455343"}, {"acronym": "DCON", "curricular_year": 5, "name": "Thesis in Building Construction", "pv_ocorrencia_id": 455344, "semester": "2", "url": "https://sigarra.up.pt/feup/en/ucurr_geral.ficha_uc_view?pv_ocorrencia_id=455344"}, {"acronym": "DGEO", "curricular_year": 5, "name": "Thesis in Geotechnics", "pv_ocorrencia_id": 455345, "semester": "2", "url": "https://sigarra.up.pt/feup/en/ucurr_geral.ficha_uc_view?pv_ocorrencia_id=455345"}, {"acronym": "DHID", "curricular_year": 5, "name": "Thesis in Hydraulics", "pv_ocorrencia_id": 455346, "semester": "2", "url": "https://sigarra.up.pt/feup/en/ucurr_geral.ficha_uc_view?pv_ocorrencia_id=455346"}, {"acronym": "DMPC", "curricular_year": 5, "name": "Thesis in Materials and Construction Processes", "pv_ocorrencia_id": 455347, "semester": "2", "url": "https://sigarra.up.pt/feup/en/ucurr_geral.ficha_uc_view?pv_ocorrencia_id=455347"}, {"acronym": "DPLA", "curricular_year": 5, "name": "Thesis in Territory Planning and Environment", "pv_ocorrencia_id": 455348, "semester": "2", "url": "https://sigarra.up.pt/feup/en/ucurr_geral.ficha_uc_view?pv_ocorrencia_id=455348"}, {"acronym": "DVCO", "curricular_year": 5, "name": "Thesis in Transport Infrastructures", "pv_ocorrencia_id": 455349, "semester": "2", "url": "https://sigarra.up.pt/feup/en/ucurr_geral.ficha_uc_view?pv_ocorrencia_id=455349"}]