[{"pv_ocorrencia_id": 460414, "start_timestamp": 1611401400.0, "finish_timestamp": 1611406800.0, "rooms": ["B120"]}, {"pv_ocorrencia_id": 460403, "start_timestamp": 1611855000.0, "finish_timestamp": 1611864000.0, "rooms": ["B111"]}, {"pv_ocorrencia_id": 460416, "start_timestamp": 1611995400.0, "finish_timestamp": 1612000800.0, "rooms": ["B225"]}, {"pv_ocorrencia_id": 460405, "start_timestamp": 1612287000.0, "finish_timestamp": 1612292400.0, "rooms": ["B335"]}, {"pv_ocorrencia_id": 460404, "start_timestamp": 1612459800.0, "finish_timestamp": 1612465200.0, "rooms": ["B214"]}]