[{"acronym": "PD", "curricular_year": 2, "name": "Dissertation Planning", "pv_ocorrencia_id": 486300, "semester": "2", "url": "https://sigarra.up.pt/feup/en/ucurr_geral.ficha_uc_view?pv_ocorrencia_id=486300"}, {"acronym": "D", "curricular_year": 2, "name": "Dissertation", "pv_ocorrencia_id": 486322, "semester": "2", "url": "https://sigarra.up.pt/feup/en/ucurr_geral.ficha_uc_view?pv_ocorrencia_id=486322"}, {"acronym": "LGP", "curricular_year": 1, "name": "Project Management Laboratory", "pv_ocorrencia_id": 486247, "semester": "2", "url": "https://sigarra.up.pt/feup/en/ucurr_geral.ficha_uc_view?pv_ocorrencia_id=486247"}, {"acronym": "ASMA", "curricular_year": 1, "name": "Agents and Multi-Agent Systems", "pv_ocorrencia_id": 486248, "semester": "2", "url": "https://sigarra.up.pt/feup/en/ucurr_geral.ficha_uc_view?pv_ocorrencia_id=486248"}, {"acronym": "ASSO", "curricular_year": 1, "name": "Software Systems Architecture", "pv_ocorrencia_id": 486249, "semester": "2", "url": "https://sigarra.up.pt/feup/en/ucurr_geral.ficha_uc_view?pv_ocorrencia_id=486249"}, {"acronym": "CAC", "curricular_year": 1, "name": "Machine Learning Complements", "pv_ocorrencia_id": 486250, "semester": "2", "url": "https://sigarra.up.pt/feup/en/ucurr_geral.ficha_uc_view?pv_ocorrencia_id=486250"}, {"acronym": "CPM", "curricular_year": 1, "name": "Mobile Computing", "pv_ocorrencia_id": 486251, "semester": "2", "url": "https://sigarra.up.pt/feup/en/ucurr_geral.ficha_uc_view?pv_ocorrencia_id=486251"}, {"acronym": "DDJD", "curricular_year": 1, "name": "Design and Development of Digital Games", "pv_ocorrencia_id": 486252, "semester": "2", "url": "https://sigarra.up.pt/feup/en/ucurr_geral.ficha_uc_view?pv_ocorrencia_id=486252"}, {"acronym": "ER", "curricular_year": 1, "name": "Requirements Engineering", "pv_ocorrencia_id": 486253, "semester": "2", "url": "https://sigarra.up.pt/feup/en/ucurr_geral.ficha_uc_view?pv_ocorrencia_id=486253"}, {"acronym": "EDAA", "curricular_year": 1, "name": "Advanced Data Structures and Algorithms", "pv_ocorrencia_id": 486254, "semester": "2", "url": "https://sigarra.up.pt/feup/en/ucurr_geral.ficha_uc_view?pv_ocorrencia_id=486254"}, {"acronym": "GEE", "curricular_year": 1, "name": "Enterprise Management and Entrepreneurship", "pv_ocorrencia_id": 486255, "semester": "2", "url": "https://sigarra.up.pt/feup/en/ucurr_geral.ficha_uc_view?pv_ocorrencia_id=486255"}, {"acronym": "GRS", "curricular_year": 1, "name": "Networks and Systems Management", "pv_ocorrencia_id": 486256, "semester": "2", "url": "https://sigarra.up.pt/feup/en/ucurr_geral.ficha_uc_view?pv_ocorrencia_id=486256"}, {"acronym": "GSSI", "curricular_year": 1, "name": "Information Systems Management", "pv_ocorrencia_id": 486258, "semester": "2", "url": "https://sigarra.up.pt/feup/en/ucurr_geral.ficha_uc_view?pv_ocorrencia_id=486258"}, {"acronym": "MK", "curricular_year": 1, "name": "Marketing", "pv_ocorrencia_id": 486259, "semester": "2", "url": "https://sigarra.up.pt/feup/en/ucurr_geral.ficha_uc_view?pv_ocorrencia_id=486259"}, {"acronym": "O", "curricular_year": 1, "name": "Optimization", "pv_ocorrencia_id": 486260, "semester": "2", "url": "https://sigarra.up.pt/feup/en/ucurr_geral.ficha_uc_view?pv_ocorrencia_id=486260"}, {"acronym": "PLN", "curricular_year": 1, "name": "Natural Language Processing", "pv_ocorrencia_id": 486261, "semester": "2", "url": "https://sigarra.up.pt/feup/en/ucurr_geral.ficha_uc_view?pv_ocorrencia_id=486261"}, {"acronym": "PLR", "curricular_year": 1, "name": "Constraint Logic Programming", "pv_ocorrencia_id": 486262, "semester": "2", "url": "https://sigarra.up.pt/feup/en/ucurr_geral.ficha_uc_view?pv_ocorrencia_id=486262"}, {"acronym": "SR", "curricular_year": 1, "name": "Network Security", "pv_ocorrencia_id": 486263, "semester": "2", "url": "https://sigarra.up.pt/feup/en/ucurr_geral.ficha_uc_view?pv_ocorrencia_id=486263"}, {"acronym": "SSI", "curricular_year": 1, "name": "Computer Systems Security", "pv_ocorrencia_id": 486264, "semester": "2", "url": "https://sigarra.up.pt/feup/en/ucurr_geral.ficha_uc_view?pv_ocorrencia_id=486264"}, {"acronym": "SAM", "curricular_year": 1, "name": "Multimedia Services and Applications", "pv_ocorrencia_id": 486265, "semester": "2", "url": "https://sigarra.up.pt/feup/en/ucurr_geral.ficha_uc_view?pv_ocorrencia_id=486265"}, {"acronym": "SETR", "curricular_year": 1, "name": "Embedded and Real Time Systems", "pv_ocorrencia_id": 486266, "semester": "2", "url": "https://sigarra.up.pt/feup/en/ucurr_geral.ficha_uc_view?pv_ocorrencia_id=486266"}, {"acronym": "TBD", "curricular_year": 1, "name": "Database Technologies", "pv_ocorrencia_id": 486267, "semester": "2", "url": "https://sigarra.up.pt/feup/en/ucurr_geral.ficha_uc_view?pv_ocorrencia_id=486267"}, {"acronym": "VC", "curricular_year": 1, "name": "Computer Vision", "pv_ocorrencia_id": 486268, "semester": "2", "url": "https://sigarra.up.pt/feup/en/ucurr_geral.ficha_uc_view?pv_ocorrencia_id=486268"}, {"acronym": "BDNR", "curricular_year": 1, "name": "Non Relational Databases", "pv_ocorrencia_id": 486269, "semester": "2", "url": "https://sigarra.up.pt/feup/en/ucurr_geral.ficha_uc_view?pv_ocorrencia_id=486269"}, {"acronym": "CPA", "curricular_year": 1, "name": "Advanced Parallel Computing", "pv_ocorrencia_id": 486270, "semester": "2", "url": "https://sigarra.up.pt/feup/en/ucurr_geral.ficha_uc_view?pv_ocorrencia_id=486270"}, {"acronym": "MFS", "curricular_year": 1, "name": "Formal Methods for Critical Systems", "pv_ocorrencia_id": 486271, "semester": "2", "url": "https://sigarra.up.pt/feup/en/ucurr_geral.ficha_uc_view?pv_ocorrencia_id=486271"}]