[{"pv_ocorrencia_id": 455081, "start_timestamp": 1614673800.0, "finish_timestamp": 1614679200.0, "rooms": ["B302"]}, {"pv_ocorrencia_id": 455113, "start_timestamp": 1614673800.0, "finish_timestamp": 1614679200.0, "rooms": []}, {"pv_ocorrencia_id": 455127, "start_timestamp": 1614778200.0, "finish_timestamp": 1614783600.0, "rooms": []}, {"pv_ocorrencia_id": 455102, "start_timestamp": 1614846600.0, "finish_timestamp": 1614852000.0, "rooms": ["B109"]}, {"pv_ocorrencia_id": 455121, "start_timestamp": 1614857400.0, "finish_timestamp": 1614862800.0, "rooms": ["B302"]}, {"pv_ocorrencia_id": 455094, "start_timestamp": 1614943800.0, "finish_timestamp": 1614949200.0, "rooms": ["B119"]}, {"pv_ocorrencia_id": 455104, "start_timestamp": 1614943800.0, "finish_timestamp": 1614949200.0, "rooms": ["B119"]}, {"pv_ocorrencia_id": 455101, "start_timestamp": 1615210200.0, "finish_timestamp": 1615215600.0, "rooms": []}, {"pv_ocorrencia_id": 455111, "start_timestamp": 1615210200.0, "finish_timestamp": 1615215600.0, "rooms": []}, {"pv_ocorrencia_id": 455060, "start_timestamp": 1615224600.0, "finish_timestamp": 1615230000.0, "rooms": []}, {"pv_ocorrencia_id": 455126, "start_timestamp": 1615289400.0, "finish_timestamp": 1615294800.0, "rooms": []}, {"pv_ocorrencia_id": 455112, "start_timestamp": 1615365000.0, "finish_timestamp": 1615370400.0, "rooms": []}, {"pv_ocorrencia_id": 455093, "start_timestamp": 1615375800.0, "finish_timestamp": 1615381200.0, "rooms": []}, {"pv_ocorrencia_id": 455125, "start_timestamp": 1615462200.0, "finish_timestamp": 1615467600.0, "rooms": []}, {"pv_ocorrencia_id": 455082, "start_timestamp": 1615570200.0, "finish_timestamp": 1615575600.0, "rooms": []}, {"pv_ocorrencia_id": 455090, "start_timestamp": 1615797000.0, "finish_timestamp": 1615802400.0, "rooms": []}, {"pv_ocorrencia_id": 455114, "start_timestamp": 1615807800.0, "finish_timestamp": 1615813200.0, "rooms": []}, {"pv_ocorrencia_id": 455122, "start_timestamp": 1615883400.0, "finish_timestamp": 1615888800.0, "rooms": []}, {"pv_ocorrencia_id": 455084, "start_timestamp": 1615894200.0, "finish_timestamp": 1615899600.0, "rooms": []}, {"pv_ocorrencia_id": 455103, "start_timestamp": 1615969800.0, "finish_timestamp": 1615975200.0, "rooms": []}, {"pv_ocorrencia_id": 455091, "start_timestamp": 1615980600.0, "finish_timestamp": 1615986000.0, "rooms": []}, {"pv_ocorrencia_id": 455115, "start_timestamp": 1616056200.0, "finish_timestamp": 1616061600.0, "rooms": []}, {"pv_ocorrencia_id": 455083, "start_timestamp": 1616088600.0, "finish_timestamp": 1616094000.0, "rooms": []}, {"pv_ocorrencia_id": 455124, "start_timestamp": 1616160600.0, "finish_timestamp": 1616166000.0, "rooms": []}, {"pv_ocorrencia_id": 455081, "start_timestamp": 1614673800.0, "finish_timestamp": 1614679200.0, "rooms": ["B302"]}, {"pv_ocorrencia_id": 455113, "start_timestamp": 1614673800.0, "finish_timestamp": 1614679200.0, "rooms": []}, {"pv_ocorrencia_id": 455099, "start_timestamp": 1614684600.0, "finish_timestamp": 1614690000.0, "rooms": []}, {"pv_ocorrencia_id": 455087, "start_timestamp": 1614760200.0, "finish_timestamp": 1614765600.0, "rooms": []}, {"pv_ocorrencia_id": 455105, "start_timestamp": 1614771000.0, "finish_timestamp": 1614776400.0, "rooms": []}, {"pv_ocorrencia_id": 455127, "start_timestamp": 1614778200.0, "finish_timestamp": 1614783600.0, "rooms": []}, {"pv_ocorrencia_id": 455102, "start_timestamp": 1614846600.0, "finish_timestamp": 1614852000.0, "rooms": ["B109"]}, {"pv_ocorrencia_id": 455121, "start_timestamp": 1614857400.0, "finish_timestamp": 1614862800.0, "rooms": ["B302"]}, {"pv_ocorrencia_id": 455086, "start_timestamp": 1614933000.0, "finish_timestamp": 1614938400.0, "rooms": []}, {"pv_ocorrencia_id": 455108, "start_timestamp": 1614933000.0, "finish_timestamp": 1614938400.0, "rooms": []}, {"pv_ocorrencia_id": 455094, "start_timestamp": 1614943800.0, "finish_timestamp": 1614949200.0, "rooms": []}, {"pv_ocorrencia_id": 455104, "start_timestamp": 1614943800.0, "finish_timestamp": 1614949200.0, "rooms": []}, {"pv_ocorrencia_id": 455120, "start_timestamp": 1615192200.0, "finish_timestamp": 1615197600.0, "rooms": []}, {"pv_ocorrencia_id": 455109, "start_timestamp": 1615203000.0, "finish_timestamp": 1615208400.0, "rooms": []}, {"pv_ocorrencia_id": 455111, "start_timestamp": 1615210200.0, "finish_timestamp": 1615215600.0, "rooms": []}, {"pv_ocorrencia_id": 455101, "start_timestamp": 1615210200.0, "finish_timestamp": 1615215600.0, "rooms": []}, {"pv_ocorrencia_id": 455060, "start_timestamp": 1615224600.0, "finish_timestamp": 1615230000.0, "rooms": []}, {"pv_ocorrencia_id": 455096, "start_timestamp": 1615278600.0, "finish_timestamp": 1615284000.0, "rooms": []}, {"pv_ocorrencia_id": 455126, "start_timestamp": 1615289400.0, "finish_timestamp": 1615294800.0, "rooms": []}, {"pv_ocorrencia_id": 455112, "start_timestamp": 1615365000.0, "finish_timestamp": 1615370400.0, "rooms": []}, {"pv_ocorrencia_id": 455089, "start_timestamp": 1615365000.0, "finish_timestamp": 1615370400.0, "rooms": []}, {"pv_ocorrencia_id": 455093, "start_timestamp": 1615375800.0, "finish_timestamp": 1615381200.0, "rooms": []}, {"pv_ocorrencia_id": 455125, "start_timestamp": 1615462200.0, "finish_timestamp": 1615467600.0, "rooms": []}, {"pv_ocorrencia_id": 455119, "start_timestamp": 1615537800.0, "finish_timestamp": 1615543200.0, "rooms": []}, {"pv_ocorrencia_id": 455098, "start_timestamp": 1615548600.0, "finish_timestamp": 1615554000.0, "rooms": []}, {"pv_ocorrencia_id": 455107, "start_timestamp": 1615555800.0, "finish_timestamp": 1615561200.0, "rooms": []}, {"pv_ocorrencia_id": 455082, "start_timestamp": 1615570200.0, "finish_timestamp": 1615575600.0, "rooms": []}, {"pv_ocorrencia_id": 455090, "start_timestamp": 1615797000.0, "finish_timestamp": 1615802400.0, "rooms": []}, {"pv_ocorrencia_id": 455114, "start_timestamp": 1615807800.0, "finish_timestamp": 1615813200.0, "rooms": []}, {"pv_ocorrencia_id": 455088, "start_timestamp": 1615807800.0, "finish_timestamp": 1615813200.0, "rooms": []}, {"pv_ocorrencia_id": 455106, "start_timestamp": 1615815000.0, "finish_timestamp": 1615820400.0, "rooms": []}, {"pv_ocorrencia_id": 455118, "start_timestamp": 1615883400.0, "finish_timestamp": 1615888800.0, "rooms": []}, {"pv_ocorrencia_id": 455122, "start_timestamp": 1615883400.0, "finish_timestamp": 1615888800.0, "rooms": []}, {"pv_ocorrencia_id": 455084, "start_timestamp": 1615894200.0, "finish_timestamp": 1615899600.0, "rooms": []}, {"pv_ocorrencia_id": 455095, "start_timestamp": 1615915800.0, "finish_timestamp": 1615921200.0, "rooms": []}, {"pv_ocorrencia_id": 455103, "start_timestamp": 1615969800.0, "finish_timestamp": 1615975200.0, "rooms": []}, {"pv_ocorrencia_id": 455110, "start_timestamp": 1615980600.0, "finish_timestamp": 1615986000.0, "rooms": []}, {"pv_ocorrencia_id": 455091, "start_timestamp": 1615980600.0, "finish_timestamp": 1615986000.0, "rooms": []}, {"pv_ocorrencia_id": 455115, "start_timestamp": 1616056200.0, "finish_timestamp": 1616061600.0, "rooms": []}, {"pv_ocorrencia_id": 455116, "start_timestamp": 1616067000.0, "finish_timestamp": 1616072400.0, "rooms": []}, {"pv_ocorrencia_id": 455083, "start_timestamp": 1616088600.0, "finish_timestamp": 1616094000.0, "rooms": []}, {"pv_ocorrencia_id": 455085, "start_timestamp": 1616142600.0, "finish_timestamp": 1616148000.0, "rooms": []}, {"pv_ocorrencia_id": 455097, "start_timestamp": 1616153400.0, "finish_timestamp": 1616158800.0, "rooms": []}, {"pv_ocorrencia_id": 455124, "start_timestamp": 1616160600.0, "finish_timestamp": 1616166000.0, "rooms": []}]